{
    "name": "App\\Models\\GrupoPessoaModel",
    "line": 14,
    "short_desc": "Modelo de Grupo de Pessoas.",
    "long_desc": "",
    "hint": null,
    "tags": {
        "package": [
            [
                "Models"
            ]
        ],
        "author": [
            [
                "Roberto",
                "Oswaldo",
                "Klann"
            ]
        ],
        "since": [
            [
                "23\/01\/2020"
            ]
        ]
    },
    "namespace": "App\\Models",
    "file": "C:\\DWR\\Apache24\\htdocs\\naj-adv-web\\configdocs\/..\/app\\Models\\GrupoPessoaModel.php",
    "relative_file": null,
    "hash": "baabf876c75c4aa80ac6c18350a7dfc95bf044fe",
    "parent": "App\\Models\\NajModel",
    "modifiers": 0,
    "is_trait": false,
    "is_interface": false,
    "aliases": {
        "NajModel": "App\\Models\\NajModel"
    },
    "errors": [],
    "interfaces": [],
    "traits": [],
    "properties": [],
    "methods": {
        "loadTable": {
            "name": "loadTable",
            "line": 16,
            "short_desc": "",
            "long_desc": "",
            "hint": null,
            "hint_desc": null,
            "tags": [],
            "modifiers": 2,
            "is_by_ref": "",
            "exceptions": [],
            "errors": [],
            "parameters": []
        },
        "getJWTIdentifier": {
            "name": "getJWTIdentifier",
            "line": 24,
            "short_desc": "",
            "long_desc": "",
            "hint": null,
            "hint_desc": null,
            "tags": [],
            "modifiers": 1,
            "is_by_ref": "",
            "exceptions": [],
            "errors": [],
            "parameters": []
        },
        "getJWTCustomClaims": {
            "name": "getJWTCustomClaims",
            "line": 28,
            "short_desc": "",
            "long_desc": "",
            "hint": null,
            "hint_desc": null,
            "tags": [],
            "modifiers": 1,
            "is_by_ref": "",
            "exceptions": [],
            "errors": [],
            "parameters": []
        }
    },
    "constants": []
}